dask_labextension/__init__.py
dask_labextension/_version.py
dask_labextension/clusterhandler.py
dask_labextension/config.py
dask_labextension/dashboardhandler.py
dask_labextension/labextension.yaml
dask_labextension/manager.py
dask_labextension/tests/__init__.py
dask_labextension/tests/test_manager.py
dask_labextension-7.0.0.data/data/etc/jupyter/jupyter_notebook_config.d/dask_labextension.json
dask_labextension-7.0.0.data/data/etc/jupyter/jupyter_server_config.d/dask_labextension.json
dask_labextension-7.0.0.data/data/share/jupyter/labextensions/dask-labextension/package.json
dask_labextension-7.0.0.data/data/share/jupyter/labextensions/dask-labextension/schemas/dask-labextension/package.json.orig
dask_labextension-7.0.0.data/data/share/jupyter/labextensions/dask-labextension/schemas/dask-labextension/plugin.json
dask_labextension-7.0.0.data/data/share/jupyter/labextensions/dask-labextension/static/11.92ba9866db6ad7a7f70f.js
dask_labextension-7.0.0.data/data/share/jupyter/labextensions/dask-labextension/static/remoteEntry.55eb452b48896f869659.js
dask_labextension-7.0.0.data/data/share/jupyter/labextensions/dask-labextension/static/style.js
dask_labextension-7.0.0.data/data/share/jupyter/labextensions/dask-labextension/static/third-party-licenses.json
dask_labextension-7.0.0.data/data/share/jupyter/labextensions/dask-labextension/install.json
dask_labextension-7.0.0.dist-info/METADATA
dask_labextension-7.0.0.dist-info/WHEEL
dask_labextension-7.0.0.dist-info/licenses/LICENSE
dask_labextension-7.0.0.dist-info/RECORD
